pytrendx/__init__.py
pytrendx/main.py
pytrendx-1.3.0.dist-info/licenses/LICENSE
pytrendx-1.3.0.dist-info/METADATA
pytrendx-1.3.0.dist-info/WHEEL
pytrendx-1.3.0.dist-info/entry_points.txt
pytrendx-1.3.0.dist-info/top_level.txt
pytrendx-1.3.0.dist-info/RECORD
